MANIFEST.in
setup.cfg
setup.py
docs/CHANGES.txt
docs/Makefile
docs/README.txt
docs/conf.py
docs/index.txt
plonesocial/__init__.py
plonesocial.auth.rpx.egg-info/PKG-INFO
plonesocial.auth.rpx.egg-info/SOURCES.txt
plonesocial.auth.rpx.egg-info/dependency_links.txt
plonesocial.auth.rpx.egg-info/entry_points.txt
plonesocial.auth.rpx.egg-info/namespace_packages.txt
plonesocial.auth.rpx.egg-info/not-zip-safe
plonesocial.auth.rpx.egg-info/paster_plugins.txt
plonesocial.auth.rpx.egg-info/requires.txt
plonesocial.auth.rpx.egg-info/top_level.txt
plonesocial/auth/__init__.py
plonesocial/auth/rpx/README.txt
plonesocial/auth/rpx/__init__.py
plonesocial/auth/rpx/config.py
plonesocial/auth/rpx/configure.zcml
plonesocial/auth/rpx/install.py
plonesocial/auth/rpx/interface.py
plonesocial/auth/rpx/plugin.py
plonesocial/auth/rpx/setuphandlers.py
plonesocial/auth/rpx/skins.zcml
plonesocial/auth/rpx/testing.txt
plonesocial/auth/rpx/browser/__init__.py
plonesocial/auth/rpx/browser/add_plugin.zpt
plonesocial/auth/rpx/browser/configlet.py
plonesocial/auth/rpx/browser/configure.zcml
plonesocial/auth/rpx/browser/icon.gif
plonesocial/auth/rpx/browser/rpx.css
plonesocial/auth/rpx/browser/rpx.js
plonesocial/auth/rpx/browser/rpx_callback.py
plonesocial/auth/rpx/browser/rpx_view.py
plonesocial/auth/rpx/locales/plonesocial.auth.rpx.pot
plonesocial/auth/rpx/locales/de/LC_MESSAGES/plonesocial.auth.rpx.mo
plonesocial/auth/rpx/locales/de/LC_MESSAGES/plonesocial.auth.rpx.po
plonesocial/auth/rpx/locales/en/LC_MESSAGES/plonesocial.auth.rpx.mo
plonesocial/auth/rpx/locales/en/LC_MESSAGES/plonesocial.auth.rpx.po
plonesocial/auth/rpx/plugins/__init__.py
plonesocial/auth/rpx/plugins/rpx.py
plonesocial/auth/rpx/portlets/__init__.py
plonesocial/auth/rpx/portlets/configure.zcml
plonesocial/auth/rpx/portlets/rpxportlet.pt
plonesocial/auth/rpx/portlets/rpxportlet.py
plonesocial/auth/rpx/profiles/default/actionicons.xml
plonesocial/auth/rpx/profiles/default/controlpanel.xml
plonesocial/auth/rpx/profiles/default/cssregistry.xml
plonesocial/auth/rpx/profiles/default/import_steps.xml
plonesocial/auth/rpx/profiles/default/jsregistry.xml
plonesocial/auth/rpx/profiles/default/memberdata_properties.xml
plonesocial/auth/rpx/profiles/default/metadata.xml
plonesocial/auth/rpx/profiles/default/portlets.xml
plonesocial/auth/rpx/profiles/default/propertiestool.xml
plonesocial/auth/rpx/profiles/default/rpx-pas.txt
