Metadata-Version: 1.0
Name: plonesocial.auth.rpx
Version: 0.815
Summary: An RPX connector for Plone, allowing users to login with Twitter, Google, Facebook etc.
Home-page: http://comlounge.net/rpx/
Author: Carsten Rebbien, Christian Scholz (COM.lounge GmbH)
Author-email: cr@comlounge.net
License: MIT
Keywords: rpx plone google twitter openid facebook yahoo janrain login identity identification authentication cms
Platform: UNKNOWN
Classifier: Development Status :: 4 - Beta
Classifier: Environment :: Web Environment
Classifier: Framework :: Plone
Classifier: Framework :: Zope2
Classifier: Intended Audience :: Developers
Classifier: Intended Audience :: End Users/Desktop
Classifier: Intended Audience :: System Administrators
Classifier: License :: OSI Approved :: MIT License
Classifier: Operating System :: OS Independent
Classifier: Programming Language :: Python
Classifier: Programming Language :: Python :: 2
Classifier: Topic :: Internet :: WWW/HTTP
Classifier: Topic :: Internet :: WWW/HTTP :: Site Management
